zope.paste-1.1.0-py3.9-nspkg.pth
zope/paste/__init__.py
zope/paste/factory.py
zope/paste/schema.xml
zope/paste/serve.py
zope/paste/tests.py
zope/paste/test_app/__init__.py
zope/paste/test_app/app.ini.in
zope/paste/test_app/app.zcml
zope/paste/test_app/favicon.ico
zope/paste/test_app/hello-world.pt
zope/paste/test_app/view.py
zope.paste-1.1.0.dist-info/LICENSE.txt
zope.paste-1.1.0.dist-info/METADATA
zope.paste-1.1.0.dist-info/WHEEL
zope.paste-1.1.0.dist-info/entry_points.txt
zope.paste-1.1.0.dist-info/namespace_packages.txt
zope.paste-1.1.0.dist-info/top_level.txt
zope.paste-1.1.0.dist-info/RECORD
