Metadata-Version: 2.1
Name: zope.paste
Version: 1.1.0
Summary: Zope 3 and PasteDeploy
Home-page: https://github.com/zopefoundation/zope.paste
Author: Sidnei da Silva and the Zope Community
Author-email: zope-dev@zope.org
License: ZPL 2.1
Keywords: web wsgi application server paste
Platform: UNKNOWN
Classifier: Development Status :: 5 - Production/Stable
Classifier: Intended Audience :: Developers
Classifier: License :: OSI Approved :: Zope Public License
Classifier: Programming Language :: Python
Classifier: Programming Language :: Python :: 3
Classifier: Programming Language :: Python :: 3.6
Classifier: Programming Language :: Python :: 3.7
Classifier: Programming Language :: Python :: 3.8
Classifier: Programming Language :: Python :: 3.9
Classifier: Programming Language :: Python :: 3.10
Classifier: Programming Language :: Python :: 3.11
Classifier: Programming Language :: Python :: Implementation :: CPython
Classifier: Natural Language :: English
Classifier: Operating System :: OS Independent
Classifier: Topic :: Internet :: WWW/HTTP
Classifier: Topic :: Software Development
License-File: LICENSE.txt
Requires-Dist: setuptools
Requires-Dist: PasteDeploy
Requires-Dist: zope.interface
Requires-Dist: zope.app.appsetup
Requires-Dist: zope.app.wsgi
Provides-Extra: test
Requires-Dist: waitress ; extra == 'test'
Requires-Dist: zope.app.publication ; extra == 'test'
Requires-Dist: zope.authentication ; extra == 'test'
Requires-Dist: zope.browserpage ; extra == 'test'
Requires-Dist: zope.component ; extra == 'test'
Requires-Dist: zope.error ; extra == 'test'
Requires-Dist: zope.principalregistry ; extra == 'test'
Requires-Dist: zope.publisher ; extra == 'test'
Requires-Dist: zope.security ; extra == 'test'
Requires-Dist: zope.site ; extra == 'test'
Requires-Dist: zope.traversing ; extra == 'test'
Requires-Dist: zope.testrunner ; extra == 'test'
Provides-Extra: test-app
Requires-Dist: waitress ; extra == 'test-app'
Requires-Dist: zope.app.publication ; extra == 'test-app'
Requires-Dist: zope.authentication ; extra == 'test-app'
Requires-Dist: zope.browserpage ; extra == 'test-app'
Requires-Dist: zope.component ; extra == 'test-app'
Requires-Dist: zope.error ; extra == 'test-app'
Requires-Dist: zope.principalregistry ; extra == 'test-app'
Requires-Dist: zope.publisher ; extra == 'test-app'
Requires-Dist: zope.security ; extra == 'test-app'
Requires-Dist: zope.site ; extra == 'test-app'
Requires-Dist: zope.traversing ; extra == 'test-app'
Requires-Dist: zope.testrunner ; extra == 'test-app'
